needle_shape_sensing/__init__.py
needle_shape_sensing/cost_functions.py
needle_shape_sensing/fbg_signal_processing.py
needle_shape_sensing/geometry.py
needle_shape_sensing/intrinsics.py
needle_shape_sensing/numerical.py
needle_shape_sensing/sensorized_needles.py
needle_shape_sensing/shape_sensing.py
needle_shape_sensing-0.1.3.dist-info/LICENSE.txt
needle_shape_sensing-0.1.3.dist-info/METADATA
needle_shape_sensing-0.1.3.dist-info/WHEEL
needle_shape_sensing-0.1.3.dist-info/top_level.txt
needle_shape_sensing-0.1.3.dist-info/RECORD
