Metadata-Version: 2.1
Name: needle-shape-sensing
Version: 0.1.3
Summary: Needle Shape Sensing library
Home-page: http://pypi.python.org/pypi/needle-shape-sensing/
Author: Dimitri Lezcano
Author-email: dlezcan1@jhu.edu
License: LICENSE.txt
Platform: UNKNOWN
Classifier: Operating System :: OS Independent
Classifier: License :: OSI Approved :: MIT License
Requires-Dist: numpy
Requires-Dist: scipy
Requires-Dist: spatialmath-python
Requires-Dist: sympy
Requires-Dist: numba
